hydra_genetics/__init__.py
hydra_genetics/__main__.py
hydra_genetics/_version.py
hydra_genetics/exceptions.py
hydra_genetics/commands/__init__.py
hydra_genetics/commands/create.py
hydra_genetics/commands/prep_pipeline_env.py
hydra_genetics/commands/references.py
hydra_genetics/pipeline-template/.gitignore
hydra_genetics/pipeline-template/.readthedocs.yaml
hydra_genetics/pipeline-template/LICENSE.md
hydra_genetics/pipeline-template/README.md
hydra_genetics/pipeline-template/mkdocs.yaml
hydra_genetics/pipeline-template/requirements.test.txt
hydra_genetics/pipeline-template/requirements.txt
hydra_genetics/pipeline-template/.github/CODEOWNERS
hydra_genetics/pipeline-template/.github/PULL_REQUEST_TEMPLATE.md
hydra_genetics/pipeline-template/.github/ISSUE_TEMPLATE/bug_report.md
hydra_genetics/pipeline-template/.github/ISSUE_TEMPLATE/feature_request.md
hydra_genetics/pipeline-template/.github/linters/.snakefmt.toml
hydra_genetics/pipeline-template/.github/linters/report/.gitkeep
hydra_genetics/pipeline-template/.github/workflows/conventional-prs.yml
hydra_genetics/pipeline-template/.github/workflows/integration.yaml
hydra_genetics/pipeline-template/.github/workflows/lint.yaml
hydra_genetics/pipeline-template/.github/workflows/pycodestyle.yaml
hydra_genetics/pipeline-template/.github/workflows/pytest.yaml
hydra_genetics/pipeline-template/.github/workflows/release-please.yaml
hydra_genetics/pipeline-template/.github/workflows/snakefmt.yaml
hydra_genetics/pipeline-template/.github/workflows/snakemake-dry-run.yaml
hydra_genetics/pipeline-template/.github/workflows/test-build-mkdocs
hydra_genetics/pipeline-template/.tests/integration/samples.tsv
hydra_genetics/pipeline-template/.tests/integration/units.tsv
hydra_genetics/pipeline-template/.tests/integration/config/config.yaml
hydra_genetics/pipeline-template/.tests/integration/config/resources.yaml
hydra_genetics/pipeline-template/config/config.yaml
hydra_genetics/pipeline-template/config/output_files.yaml
hydra_genetics-3.3.1.dist-info/licenses/LICENSE.md
hydra_genetics-3.3.1.dist-info/METADATA
hydra_genetics-3.3.1.dist-info/WHEEL
hydra_genetics-3.3.1.dist-info/entry_points.txt
hydra_genetics-3.3.1.dist-info/top_level.txt
hydra_genetics-3.3.1.dist-info/RECORD
