Metadata-Version: 2.4
Name: hydra-genetics
Version: 3.3.1
Summary: Helper tools for use with hydra-genetics pipelines.
Home-page: https://github.com/hydra-genetics/tools
Author: Patrik Smeds
Author-email: patrik.smeds@scilifelab.uu.se
License: GPL-3
Keywords: hydra-genetics,snakemake,bioinformatics,workflow,pipeline,clinical,biology,sequencing,NGS,next generation sequencing
License-File: LICENSE.md
Requires-Dist: pandas>=1.3.1
Requires-Dist: click<9,>=8
Requires-Dist: jinja2==3.0.1
Requires-Dist: rich==10.9.0
Requires-Dist: snakemake
Requires-Dist: pysam
Requires-Dist: gitpython
Requires-Dist: pyaml
Dynamic: author
Dynamic: author-email
Dynamic: description
Dynamic: description-content-type
Dynamic: home-page
Dynamic: keywords
Dynamic: license
Dynamic: license-file
Dynamic: requires-dist
Dynamic: summary
